{
"type": "FeatureCollection",
"name": "Food collection centers",
"crs": { "type": "name", "properties": { "name": "urn:ogc:def:crs:OGC:1.3:CRS84" } },
"features": [
{ "type": "Feature", "properties": { "Name": "Margao Food Bank at Lar De Santa Terezinha, next to Mario Miranda's gallery, Pajifond, Margao", "description": "One of 12 food banks started by Street Providence. We accept food for the poor and the needy from hotels, restaurants, weddings, bakery, etc. You may deposit the food (in good condition) at our centre which is quipped with freezer. " }, "geometry": { "type": "Point", "coordinates": [ 73.9626217, 15.2762781 ] } },
{ "type": "Feature", "properties": { "Name": "Peace Haven Food Bank", "description": "CTC: 9049018429" }, "geometry": { "type": "Point", "coordinates": [ 73.808303, 15.470038 ] } },
{ "type": "Feature", "properties": { "Name": "St. Joseph's Church Food Bank", "description": "CTC: 9820614033" }, "geometry": { "type": "Point", "coordinates": [ 73.797012, 15.716815 ] } },
{ "type": "Feature", "properties": { "Name": "Cafe Don Pedro Food Bank", "description": "CTC: 9890191147" }, "geometry": { "type": "Point", "coordinates": [ 73.824262, 15.396606 ] } },
{ "type": "Feature", "properties": { "Name": "Church of St Francis of Assisi Food Bank", "description": "CTC:9850185085" }, "geometry": { "type": "Point", "coordinates": [ 73.830773, 15.648652 ] } },
{ "type": "Feature", "properties": { "Name": "Immaculate Conception Church Food Bank", "description": "CTC: 9822686287" }, "geometry": { "type": "Point", "coordinates": [ 73.829618, 15.498598 ] } },
{ "type": "Feature", "properties": { "Name": "Institute Piedade Food Bank", "description": "CTC: 9423888255" }, "geometry": { "type": "Point", "coordinates": [ 73.825158, 15.495588 ] } },
{ "type": "Feature", "properties": { "Name": "Archbishop's Palace Food Bank", "description": "CTC: 9822103474" }, "geometry": { "type": "Point", "coordinates": [ 73.826184, 15.491911 ] } },
{ "type": "Feature", "properties": { "Name": "our lady of grace church Food Bank", "description": "CTC: 7083039949" }, "geometry": { "type": "Point", "coordinates": [ 73.947553, 15.5893 ] } },
{ "type": "Feature", "properties": { "Name": "Holy Cross Shrine Bambolim", "description": "CTC: 9822418870" }, "geometry": { "type": "Point", "coordinates": [ 73.864281, 15.452149 ] } },
{ "type": "Feature", "properties": { "Name": "St Clara's Church", "description": "CTC: 9822137027" }, "geometry": { "type": "Point", "coordinates": [ 73.894549, 15.618564 ] } },
{ "type": "Feature", "properties": { "Name": "St.Mary’s  Convent", "description": "CTC: 8459995729" }, "geometry": { "type": "Point", "coordinates": [ 74.013747, 15.402305 ] } },
{ "type": "Feature", "properties": { "Name": "Mãe de Deus Chapel", "description": "CTC: 8805043638" }, "geometry": { "type": "Point", "coordinates": [ 73.785752, 15.621926 ] } },
{ "type": "Feature", "properties": { "Name": "Fr. Agnel College Food Bank", "description": "CTC: 9822177441" }, "geometry": { "type": "Point", "coordinates": [ 73.893715, 15.439251 ] } },
{ "type": "Feature", "properties": { "Name": "Lar de Sant. Terezinha", "description": "Food Bank CTC:9850152860" }, "geometry": { "type": "Point", "coordinates": [ 73.963282, 15.276226 ] } },
{ "type": "Feature", "properties": { "Name": "Lar Da Santa Clara FHIC", "description": "Food Bank CTC: 8606310169" }, "geometry": { "type": "Point", "coordinates": [ 73.956896, 15.279211 ] } },
{ "type": "Feature", "properties": { "Name": "St. Matthews Church Food Bank", "description": "CTC: 9158440364" }, "geometry": { "type": "Point", "coordinates": [ 73.920921, 15.464846 ] } },
{ "type": "Feature", "properties": { "Name": "Convent of our Lady Angels Food Bank", "description": "CTC: 9767237266" }, "geometry": { "type": "Point", "coordinates": [ 73.909597, 15.499524 ] } },
{ "type": "Feature", "properties": { "Name": "Gauri Car Center Petrol Pump Food Bank", "description": "CTC: 9921939797" }, "geometry": { "type": "Point", "coordinates": [ 73.829136, 15.519256 ] } },
{ "type": "Feature", "properties": { "Name": "HP PETROL PUMP - FUEL POINT, FOOD  BANK", "description": "CTC: 9822127899" }, "geometry": { "type": "Point", "coordinates": [ 73.818664, 15.399001 ] } },
{ "type": "Feature", "properties": { "Name": "Cravings Cakes, FOOD BANK", "description": "CTC: 8805309016" }, "geometry": { "type": "Point", "coordinates": [ 73.780855, 15.561076 ] } },
{ "type": "Feature", "properties": { "Name": "Our Lady of Mount Carmel, Food Bank", "description": "CTC: 9822581460" }, "geometry": { "type": "Point", "coordinates": [ 73.715778, 15.696895 ] } },
{ "type": "Feature", "properties": { "Name": "Succor Home, Food Bank", "description": "Food Bank 20 Meters away from BLUE LAGOON APARTMENTS , CTC: 8805602898\/9226444249" }, "geometry": { "type": "Point", "coordinates": [ 73.773434, 15.624016 ] } },
{ "type": "Feature", "properties": { "Name": "House of Mercy, Mapusa FOOD BANK", "description": "Food Bank Next to Mosque, Near Old Aldona Bus stand, CTC: 8286512145" }, "geometry": { "type": "Point", "coordinates": [ 73.812985, 15.589006 ] } },
{ "type": "Feature", "properties": { "Name": "St. Agnes Church, St. Inez, FOOD BANK", "description": "St.Agnes Church Food Bank is Few Meters away from Viventa Taj, CTC: 9822489189" }, "geometry": { "type": "Point", "coordinates": [ 73.820528, 15.494008 ] } },
{ "type": "Feature", "properties": { "Name": "Divine Providence Convent, Benaulim FOOD BANK", "description": "CTC: 9890917570" }, "geometry": { "type": "Point", "coordinates": [ 73.933863, 15.27339 ] } },
{ "type": "Feature", "properties": { "Name": "Velim FOOD BANK", "description": "Velim Food Bank Near St. Francis Xavier Church, Velim,  CTC: 7350537035" }, "geometry": { "type": "Point", "coordinates": [ 73.974081, 15.165727 ] } },
{ "type": "Feature", "properties": { "Name": "Sangolda Food Bank", "description": "Sangolda Food Bank is 20 meters away from Muktar Automobiles, CTC: 8380097564" }, "geometry": { "type": "Point", "coordinates": [ 73.812027, 15.543235 ] } },
{ "type": "Feature", "properties": { "Name": "Our Lady of Martyrs Church, Assolna Food Bank", "description": "CTC: 7507390034" }, "geometry": { "type": "Point", "coordinates": [ 73.970173, 15.183211 ] } }
]
}
